knightswhosayni/__init__.py
knightswhosayni/admin.py
knightswhosayni/apps.py
knightswhosayni/forms.py
knightswhosayni/main.py
knightswhosayni/models.py
knightswhosayni/template_init.py
knightswhosayni/urls.py
knightswhosayni/utils.py
knightswhosayni/views.py
knightswhosayni/migrations/0001_initial.py
knightswhosayni/migrations/0002_auto_20230307_0633.py
knightswhosayni/migrations/0003_project_module_name.py
knightswhosayni/migrations/0004_sale.py
knightswhosayni/migrations/0005_sale_license.py
knightswhosayni/migrations/0006_auto_20230321_0442.py
knightswhosayni/migrations/0007_project_logo.py
knightswhosayni/migrations/__init__.py
knightswhosayni-0.2.0.dist-info/LICENSE
knightswhosayni-0.2.0.dist-info/METADATA
knightswhosayni-0.2.0.dist-info/WHEEL
knightswhosayni-0.2.0.dist-info/entry_points.txt
knightswhosayni-0.2.0.dist-info/top_level.txt
knightswhosayni-0.2.0.dist-info/RECORD
