Metadata-Version: 2.1
Name: knightswhosayni
Version: 0.2.0
Summary: Ni! Ni! Ni!
Author-email: Grant Jenks <contact@grantjenks.com>
License: Apache 2.0
Project-URL: Documentation, https://grantjenks.com/docs/knightswhosayni/
Project-URL: Funding, https://gum.co/knightswhosayni
Project-URL: Source, https://github.com/grantjenks/knights-who-say-ni
Project-URL: Tracker, https://github.com/grantjenks/knights-who-say-ni/issues
Keywords: licensing,encoding
Classifier: Development Status :: 5 - Production/Stable
Classifier: License :: OSI Approved :: Apache Software License
Classifier: Natural Language :: English
Classifier: Programming Language :: Python
Classifier: Programming Language :: Python :: 3
Requires-Python: >=3.7
License-File: LICENSE
Requires-Dist: Django
Requires-Dist: Pillow
Requires-Dist: requests
